{"candlesticks": [{"end_period_ts": 1783742400, "open_interest_fp": "21158243.77", "price": {"close_dollars": "0.1480", "high_dollars": "0.1500", "low_dollars": "0.1470", "mean_dollars": "0.1478", "open_dollars": "0.1480", "previous_dollars": "0.1480"}, "volume_fp": "42592.76", "yes_ask": {"close_dollars": "0.1480", "high_dollars": "0.1510", "low_dollars": "0.1480", "open_dollars": "0.1480"}, "yes_bid": {"close_dollars": "0.1470", "high_dollars": "0.1480", "low_dollars": "0.1470", "open_dollars": "0.1470"}}, {"end_period_ts": 1783746000, "open_interest_fp": "21157696.31", "price": {"close_dollars": "0.1470", "high_dollars": "0.1480", "low_dollars": "0.1470", "mean_dollars": "0.1474", "open_dollars": "0.1470", "previous_dollars": "0.1480"}, "volume_fp": "36632.21", "yes_ask": {"close_dollars": "0.1480", "high_dollars": "0.1480", "low_dollars": "0.1480", "open_dollars": "0.1480"}, "yes_bid": {"close_dollars": "0.1470", "high_dollars": "0.1470", "low_dollars": "0.1470", "open_dollars": "0.1470"}}, {"end_period_ts": 1783749600, "open_interest_fp": "21207560.73", "price": {"close_dollars": "0.1480", "high_dollars": "0.1540", "low_dollars": "0.1470", "mean_dollars": "0.1486", "open_dollars": "0.1480", "previous_dollars": "0.1470"}, "volume_fp": "54753.53", "yes_ask": {"close_dollars": "0.1480", "high_dollars": "0.1540", "low_dollars": "0.1480", "open_dollars": "0.1480"}, "yes_bid": {"close_dollars": "0.1470", "high_dollars": "0.1480", "low_dollars": "0.1470", "open_dollars": "0.1470"}}, {"end_period_ts": 1783753200, "open_interest_fp": "21217669.11", "price": {"close_dollars": "0.1470", "high_dollars": "0.1480", "low_dollars": "0.1470", "mean_dollars": "0.1479", "open_dollars": "0.1480", "previous_dollars": "0.1480"}, "volume_fp": "11471.72", "yes_ask": {"close_dollars": "0.1480", "high_dollars": "0.1480", "low_dollars": "0.1480", "open_dollars": "0.1480"}, "yes_bid": {"close_dollars": "0.1470", "high_dollars": "0.1470", "low_dollars": "0.1470", "open_dollars": "0.1470"}}, {"end_period_ts": 1783756800, "open_interest_fp": "21223200.87", "price": {"close_dollars": "0.1480", "high_dollars": "0.1480", "low_dollars": "0.1470", "mean_dollars": "0.1477", "open_dollars": "0.1480", "previous_dollars": "0.1470"}, "volume_fp": "9990.54", "yes_ask": {"close_dollars": "0.1480", "high_dollars": "0.1480", "low_dollars": "0.1480", "open_dollars": "0.1480"}, "yes_bid": {"close_dollars": "0.1470", "high_dollars": "0.1470", "low_dollars": "0.1470", "open_dollars": "0.1470"}}, {"end_period_ts": 1783760400, "open_interest_fp": "21230456.71", "price": {"close_dollars": "0.1480", "high_dollars": "0.1480", "low_dollars": "0.1470", "mean_dollars": "0.1479", "open_dollars": "0.1480", "previous_dollars": "0.1480"}, "volume_fp": "8152.40", "yes_ask": {"close_dollars": "0.1480", "high_dollars": "0.1480", "low_dollars": "0.1480", "open_dollars": "0.1480"}, "yes_bid": {"close_dollars": "0.1470", "high_dollars": "0.1470", "low_dollars": "0.1470", "open_dollars": "0.1470"}}, {"end_period_ts": 1783764000, "open_interest_fp": "21231769.45", "price": {"close_dollars": "0.1480", "high_dollars": "0.1480", "low_dollars": "0.1470", "mean_dollars": "0.1477", "open_dollars": "0.1480", "previous_dollars": "0.1480"}, "volume_fp": "1754.35", "yes_ask": {"close_dollars": "0.1480", "high_dollars": "0.1480", "low_dollars": "0.1480", "open_dollars": "0.1480"}, "yes_bid": {"close_dollars": "0.1470", "high_dollars": "0.1470", "low_dollars": "0.1470", "open_dollars": "0.1470"}}, {"end_period_ts": 1783767600, "open_interest_fp": "21236871.90", "price": {"close_dollars": "0.1470", "high_dollars": "0.1480", "low_dollars": "0.1470", "mean_dollars": "0.1479", "open_dollars": "0.1480", "previous_dollars": "0.1480"}, "volume_fp": "10024.97", "yes_ask": {"close_dollars": "0.1480", "high_dollars": "0.1480", "low_dollars": "0.1480", "open_dollars": "0.1480"}, "yes_bid": {"close_dollars": "0.1470", "high_dollars": "0.1470", "low_dollars": "0.1470", "open_dollars": "0.1470"}}, {"end_period_ts": 1783771200, "open_interest_fp": "21242375.21", "price": {"close_dollars": "0.1480", "high_dollars": "0.1480", "low_dollars": "0.1470", "mean_dollars": "0.1479", "open_dollars": "0.1470", "previous_dollars": "0.1470"}, "volume_fp": "9456.48", "yes_ask": {"close_dollars": "0.1480", "high_dollars": "0.1480", "low_dollars": "0.1480", "open_dollars": "0.1480"}, "yes_bid": {"close_dollars": "0.1470", "high_dollars": "0.1470", "low_dollars": "0.1470", "open_dollars": "0.1470"}}, {"end_period_ts": 1783774800, "open_interest_fp": "21245883.40", "price": {"close_dollars": "0.1480", "high_dollars": "0.1480", "low_dollars": "0.1470", "mean_dollars": "0.1478", "open_dollars": "0.1480", "previous_dollars": "0.1480"}, "volume_fp": "5536.12", "yes_ask": {"close_dollars": "0.1480", "high_dollars": "0.1480", "low_dollars": "0.1480", "open_dollars": "0.1480"}, "yes_bid": {"close_dollars": "0.1470", "high_dollars": "0.1470", "low_dollars": "0.1470", "open_dollars": "0.1470"}}, {"end_period_ts": 1783778400, "open_interest_fp": "21257684.66", "price": {"close_dollars": "0.1470", "high_dollars": "0.1520", "low_dollars": "0.1460", "mean_dollars": "0.1475", "open_dollars": "0.1470", "previous_dollars": "0.1480"}, "volume_fp": "16234.26", "yes_ask": {"close_dollars": "0.1470", "high_dollars": "0.1520", "low_dollars": "0.1470", "open_dollars": "0.1480"}, "yes_bid": {"close_dollars": "0.1460", "high_dollars": "0.1480", "low_dollars": "0.1460", "open_dollars": "0.1470"}}, {"end_period_ts": 1783782000, "open_interest_fp": "21262414.87", "price": {"close_dollars": "0.1450", "high_dollars": "0.1470", "low_dollars": "0.1440", "mean_dollars": "0.1457", "open_dollars": "0.1470", "previous_dollars": "0.1470"}, "volume_fp": "10031.21", "yes_ask": {"close_dollars": "0.1450", "high_dollars": "0.1480", "low_dollars": "0.1450", "open_dollars": "0.1470"}, "yes_bid": {"close_dollars": "0.1440", "high_dollars": "0.1460", "low_dollars": "0.1440", "open_dollars": "0.1460"}}, {"end_period_ts": 1783785600, "open_interest_fp": "21278337.01", "price": {"close_dollars": "0.1450", "high_dollars": "0.1450", "low_dollars": "0.1440", "mean_dollars": "0.1449", "open_dollars": "0.1450", "previous_dollars": "0.1450"}, "volume_fp": "19862.76", "yes_ask": {"close_dollars": "0.1450", "high_dollars": "0.1450", "low_dollars": "0.1450", "open_dollars": "0.1450"}, "yes_bid": {"close_dollars": "0.1440", "high_dollars": "0.1440", "low_dollars": "0.1440", "open_dollars": "0.1440"}}, {"end_period_ts": 1783789200, "open_interest_fp": "21346715.74", "price": {"close_dollars": "0.1450", "high_dollars": "0.1480", "low_dollars": "0.1440", "mean_dollars": "0.1458", "open_dollars": "0.1440", "previous_dollars": "0.1450"}, "volume_fp": "77660.84", "yes_ask": {"close_dollars": "0.1450", "high_dollars": "0.1480", "low_dollars": "0.1450", "open_dollars": "0.1450"}, "yes_bid": {"close_dollars": "0.1440", "high_dollars": "0.1470", "low_dollars": "0.1440", "open_dollars": "0.1440"}}, {"end_period_ts": 1783792800, "open_interest_fp": "21349351.70", "price": {"close_dollars": "0.1440", "high_dollars": "0.1450", "low_dollars": "0.1440", "mean_dollars": "0.1445", "open_dollars": "0.1440", "previous_dollars": "0.1450"}, "volume_fp": "32480.00", "yes_ask": {"close_dollars": "0.1450", "high_dollars": "0.1450", "low_dollars": "0.1450", "open_dollars": "0.1450"}, "yes_bid": {"close_dollars": "0.1440", "high_dollars": "0.1440", "low_dollars": "0.1440", "open_dollars": "0.1440"}}, {"end_period_ts": 1783796400, "open_interest_fp": "21385112.92", "price": {"close_dollars": "0.1440", "high_dollars": "0.1450", "low_dollars": "0.1440", "mean_dollars": "0.1447", "open_dollars": "0.1450", "previous_dollars": "0.1440"}, "volume_fp": "46867.86", "yes_ask": {"close_dollars": "0.1450", "high_dollars": "0.1450", "low_dollars": "0.1450", "open_dollars": "0.1450"}, "yes_bid": {"close_dollars": "0.1440", "high_dollars": "0.1440", "low_dollars": "0.1440", "open_dollars": "0.1440"}}, {"end_period_ts": 1783800000, "open_interest_fp": "21444744.21", "price": {"close_dollars": "0.1470", "high_dollars": "0.1490", "low_dollars": "0.1440", "mean_dollars": "0.1465", "open_dollars": "0.1440", "previous_dollars": "0.1440"}, "volume_fp": "86605.61", "yes_ask": {"close_dollars": "0.1470", "high_dollars": "0.1490", "low_dollars": "0.1450", "open_dollars": "0.1450"}, "yes_bid": {"close_dollars": "0.1460", "high_dollars": "0.1470", "low_dollars": "0.1440", "open_dollars": "0.1440"}}, {"end_period_ts": 1783803600, "open_interest_fp": "21579347.74", "price": {"close_dollars": "0.1490", "high_dollars": "0.1490", "low_dollars": "0.1460", "mean_dollars": "0.1480", "open_dollars": "0.1470", "previous_dollars": "0.1470"}, "volume_fp": "163236.19", "yes_ask": {"close_dollars": "0.1500", "high_dollars": "0.1500", "low_dollars": "0.1470", "open_dollars": "0.1470"}, "yes_bid": {"close_dollars": "0.1490", "high_dollars": "0.1490", "low_dollars": "0.1460", "open_dollars": "0.1460"}}, {"end_period_ts": 1783807200, "open_interest_fp": "21614484.24", "price": {"close_dollars": "0.1510", "high_dollars": "0.1690", "low_dollars": "0.0800", "mean_dollars": "0.1247", "open_dollars": "0.1500", "previous_dollars": "0.1490"}, "volume_fp": "202826.27", "yes_ask": {"close_dollars": "0.1510", "high_dollars": "0.1690", "low_dollars": "0.0880", "open_dollars": "0.1500"}, "yes_bid": {"close_dollars": "0.1500", "high_dollars": "0.1600", "low_dollars": "0.0800", "open_dollars": "0.1490"}}, {"end_period_ts": 1783810800, "open_interest_fp": "21621336.63", "price": {"close_dollars": "0.1270", "high_dollars": "0.1690", "low_dollars": "0.0800", "mean_dollars": "0.1286", "open_dollars": "0.1510", "previous_dollars": "0.1510"}, "volume_fp": "173997.44", "yes_ask": {"close_dollars": "0.1270", "high_dollars": "0.1700", "low_dollars": "0.0910", "open_dollars": "0.1510"}, "yes_bid": {"close_dollars": "0.1200", "high_dollars": "0.1500", "low_dollars": "0.0800", "open_dollars": "0.1500"}}, {"end_period_ts": 1783814400, "open_interest_fp": "21626107.91", "price": {"close_dollars": "0.2050", "high_dollars": "0.2130", "low_dollars": "0.1100", "mean_dollars": "0.1865", "open_dollars": "0.1270", "previous_dollars": "0.1270"}, "volume_fp": "351247.51", "yes_ask": {"close_dollars": "0.2050", "high_dollars": "0.2130", "low_dollars": "0.1160", "open_dollars": "0.1270"}, "yes_bid": {"close_dollars": "0.1990", "high_dollars": "0.2060", "low_dollars": "0.1100", "open_dollars": "0.1200"}}, {"end_period_ts": 1783818000, "open_interest_fp": "21633200.43", "price": {"close_dollars": "0.2020", "high_dollars": "0.2070", "low_dollars": "0.1980", "mean_dollars": "0.2064", "open_dollars": "0.2050", "previous_dollars": "0.2050"}, "volume_fp": "192575.65", "yes_ask": {"close_dollars": "0.2020", "high_dollars": "0.2070", "low_dollars": "0.2000", "open_dollars": "0.2050"}, "yes_bid": {"close_dollars": "0.2010", "high_dollars": "0.2060", "low_dollars": "0.1980", "open_dollars": "0.1990"}}, {"end_period_ts": 1783821600, "open_interest_fp": "21649619.96", "price": {"close_dollars": "0.1900", "high_dollars": "0.2090", "low_dollars": "0.1800", "mean_dollars": "0.1993", "open_dollars": "0.2040", "previous_dollars": "0.2020"}, "volume_fp": "136077.98", "yes_ask": {"close_dollars": "0.1990", "high_dollars": "0.2090", "low_dollars": "0.1890", "open_dollars": "0.2020"}, "yes_bid": {"close_dollars": "0.1920", "high_dollars": "0.2060", "low_dollars": "0.1800", "open_dollars": "0.2010"}}, {"end_period_ts": 1783825200, "open_interest_fp": "21655339.59", "price": {"close_dollars": "0.2180", "high_dollars": "0.2400", "low_dollars": "0.1880", "mean_dollars": "0.2142", "open_dollars": "0.1990", "previous_dollars": "0.1900"}, "volume_fp": "69900.87", "yes_ask": {"close_dollars": "0.2180", "high_dollars": "0.2400", "low_dollars": "0.1930", "open_dollars": "0.1990"}, "yes_bid": {"close_dollars": "0.2020", "high_dollars": "0.2250", "low_dollars": "0.1880", "open_dollars": "0.1920"}}, {"end_period_ts": 1783828800, "open_interest_fp": "21699701.39", "price": {"close_dollars": "0.2050", "high_dollars": "0.2450", "low_dollars": "0.1950", "mean_dollars": "0.2169", "open_dollars": "0.2170", "previous_dollars": "0.2180"}, "volume_fp": "183588.83", "yes_ask": {"close_dollars": "0.2060", "high_dollars": "0.2490", "low_dollars": "0.2000", "open_dollars": "0.2180"}, "yes_bid": {"close_dollars": "0.2050", "high_dollars": "0.2400", "low_dollars": "0.1950", "open_dollars": "0.2020"}}], "ticker": "KXMENWORLDCUP-26-GB"}