{"candlesticks": [{"end_period_ts": 1779681600, "open_interest_fp": "947167.53", "price": {"close_dollars": "0.0510", "high_dollars": "0.0510", "low_dollars": "0.0500", "mean_dollars": "0.0508", "open_dollars": "0.0510", "previous_dollars": "0.0510"}, "volume_fp": "38269.00", "yes_ask": {"close_dollars": "0.0510", "high_dollars": "0.0510", "low_dollars": "0.0510", "open_dollars": "0.0510"}, "yes_bid": {"close_dollars": "0.0500", "high_dollars": "0.0500", "low_dollars": "0.0500", "open_dollars": "0.0500"}}, {"end_period_ts": 1779768000, "open_interest_fp": "970568.14", "price": {"close_dollars": "0.0510", "high_dollars": "0.0510", "low_dollars": "0.0500", "mean_dollars": "0.0509", "open_dollars": "0.0510", "previous_dollars": "0.0510"}, "volume_fp": "25692.63", "yes_ask": {"close_dollars": "0.0510", "high_dollars": "0.0510", "low_dollars": "0.0510", "open_dollars": "0.0510"}, "yes_bid": {"close_dollars": "0.0500", "high_dollars": "0.0500", "low_dollars": "0.0500", "open_dollars": "0.0500"}}, {"end_period_ts": 1779854400, "open_interest_fp": "1060187.86", "price": {"close_dollars": "0.0530", "high_dollars": "0.0530", "low_dollars": "0.0500", "mean_dollars": "0.0511", "open_dollars": "0.0510", "previous_dollars": "0.0510"}, "volume_fp": "94040.32", "yes_ask": {"close_dollars": "0.0530", "high_dollars": "0.0530", "low_dollars": "0.0510", "open_dollars": "0.0510"}, "yes_bid": {"close_dollars": "0.0520", "high_dollars": "0.0520", "low_dollars": "0.0500", "open_dollars": "0.0500"}}, {"end_period_ts": 1779940800, "open_interest_fp": "1088682.72", "price": {"close_dollars": "0.0560", "high_dollars": "0.0560", "low_dollars": "0.0520", "mean_dollars": "0.0557", "open_dollars": "0.0530", "previous_dollars": "0.0530"}, "volume_fp": "29484.55", "yes_ask": {"close_dollars": "0.0560", "high_dollars": "0.0560", "low_dollars": "0.0530", "open_dollars": "0.0530"}, "yes_bid": {"close_dollars": "0.0550", "high_dollars": "0.0550", "low_dollars": "0.0510", "open_dollars": "0.0520"}}, {"end_period_ts": 1780027200, "open_interest_fp": "1104663.72", "price": {"close_dollars": "0.0550", "high_dollars": "0.0560", "low_dollars": "0.0530", "mean_dollars": "0.0560", "open_dollars": "0.0560", "previous_dollars": "0.0560"}, "volume_fp": "16182.32", "yes_ask": {"close_dollars": "0.0560", "high_dollars": "0.0560", "low_dollars": "0.0550", "open_dollars": "0.0560"}, "yes_bid": {"close_dollars": "0.0550", "high_dollars": "0.0550", "low_dollars": "0.0530", "open_dollars": "0.0550"}}, {"end_period_ts": 1780113600, "open_interest_fp": "1149439.18", "price": {"close_dollars": "0.0560", "high_dollars": "0.0560", "low_dollars": "0.0530", "mean_dollars": "0.0559", "open_dollars": "0.0560", "previous_dollars": "0.0550"}, "volume_fp": "48642.55", "yes_ask": {"close_dollars": "0.0560", "high_dollars": "0.0560", "low_dollars": "0.0550", "open_dollars": "0.0560"}, "yes_bid": {"close_dollars": "0.0550", "high_dollars": "0.0550", "low_dollars": "0.0530", "open_dollars": "0.0550"}}, {"end_period_ts": 1780200000, "open_interest_fp": "1196663.88", "price": {"close_dollars": "0.0560", "high_dollars": "0.0560", "low_dollars": "0.0530", "mean_dollars": "0.0553", "open_dollars": "0.0560", "previous_dollars": "0.0560"}, "volume_fp": "61862.66", "yes_ask": {"close_dollars": "0.0560", "high_dollars": "0.0560", "low_dollars": "0.0540", "open_dollars": "0.0560"}, "yes_bid": {"close_dollars": "0.0550", "high_dollars": "0.0550", "low_dollars": "0.0530", "open_dollars": "0.0550"}}, {"end_period_ts": 1780286400, "open_interest_fp": "1321069.92", "price": {"close_dollars": "0.0560", "high_dollars": "0.0570", "low_dollars": "0.0530", "mean_dollars": "0.0559", "open_dollars": "0.0560", "previous_dollars": "0.0560"}, "volume_fp": "136962.43", "yes_ask": {"close_dollars": "0.0560", "high_dollars": "0.0570", "low_dollars": "0.0540", "open_dollars": "0.0560"}, "yes_bid": {"close_dollars": "0.0550", "high_dollars": "0.0560", "low_dollars": "0.0530", "open_dollars": "0.0550"}}, {"end_period_ts": 1780372800, "open_interest_fp": "1459538.01", "price": {"close_dollars": "0.0580", "high_dollars": "0.0590", "low_dollars": "0.0550", "mean_dollars": "0.0568", "open_dollars": "0.0560", "previous_dollars": "0.0560"}, "volume_fp": "167489.08", "yes_ask": {"close_dollars": "0.0580", "high_dollars": "0.0590", "low_dollars": "0.0560", "open_dollars": "0.0560"}, "yes_bid": {"close_dollars": "0.0570", "high_dollars": "0.0580", "low_dollars": "0.0550", "open_dollars": "0.0550"}}, {"end_period_ts": 1780459200, "open_interest_fp": "1550189.16", "price": {"close_dollars": "0.0580", "high_dollars": "0.0580", "low_dollars": "0.0570", "mean_dollars": "0.0579", "open_dollars": "0.0580", "previous_dollars": "0.0580"}, "volume_fp": "105309.75", "yes_ask": {"close_dollars": "0.0580", "high_dollars": "0.0580", "low_dollars": "0.0580", "open_dollars": "0.0580"}, "yes_bid": {"close_dollars": "0.0570", "high_dollars": "0.0570", "low_dollars": "0.0570", "open_dollars": "0.0570"}}, {"end_period_ts": 1780545600, "open_interest_fp": "1595643.74", "price": {"close_dollars": "0.0580", "high_dollars": "0.0580", "low_dollars": "0.0570", "mean_dollars": "0.0579", "open_dollars": "0.0580", "previous_dollars": "0.0580"}, "volume_fp": "51854.38", "yes_ask": {"close_dollars": "0.0580", "high_dollars": "0.0580", "low_dollars": "0.0580", "open_dollars": "0.0580"}, "yes_bid": {"close_dollars": "0.0570", "high_dollars": "0.0570", "low_dollars": "0.0570", "open_dollars": "0.0570"}}, {"end_period_ts": 1780632000, "open_interest_fp": "1770317.83", "price": {"close_dollars": "0.0580", "high_dollars": "0.0580", "low_dollars": "0.0570", "mean_dollars": "0.0579", "open_dollars": "0.0570", "previous_dollars": "0.0580"}, "volume_fp": "187905.58", "yes_ask": {"close_dollars": "0.0580", "high_dollars": "0.0580", "low_dollars": "0.0580", "open_dollars": "0.0580"}, "yes_bid": {"close_dollars": "0.0570", "high_dollars": "0.0570", "low_dollars": "0.0570", "open_dollars": "0.0570"}}, {"end_period_ts": 1780718400, "open_interest_fp": "2239625.99", "price": {"close_dollars": "0.0600", "high_dollars": "0.0600", "low_dollars": "0.0580", "mean_dollars": "0.0586", "open_dollars": "0.0580", "previous_dollars": "0.0580"}, "volume_fp": "484591.27", "yes_ask": {"close_dollars": "0.0600", "high_dollars": "0.0600", "low_dollars": "0.0580", "open_dollars": "0.0580"}, "yes_bid": {"close_dollars": "0.0590", "high_dollars": "0.0590", "low_dollars": "0.0570", "open_dollars": "0.0570"}}, {"end_period_ts": 1780804800, "open_interest_fp": "2297137.68", "price": {"close_dollars": "0.0600", "high_dollars": "0.0600", "low_dollars": "0.0590", "mean_dollars": "0.0595", "open_dollars": "0.0600", "previous_dollars": "0.0600"}, "volume_fp": "114161.93", "yes_ask": {"close_dollars": "0.0600", "high_dollars": "0.0600", "low_dollars": "0.0600", "open_dollars": "0.0600"}, "yes_bid": {"close_dollars": "0.0590", "high_dollars": "0.0590", "low_dollars": "0.0590", "open_dollars": "0.0590"}}, {"end_period_ts": 1780891200, "open_interest_fp": "2348307.25", "price": {"close_dollars": "0.0600", "high_dollars": "0.0600", "low_dollars": "0.0590", "mean_dollars": "0.0598", "open_dollars": "0.0600", "previous_dollars": "0.0600"}, "volume_fp": "60351.30", "yes_ask": {"close_dollars": "0.0600", "high_dollars": "0.0600", "low_dollars": "0.0600", "open_dollars": "0.0600"}, "yes_bid": {"close_dollars": "0.0590", "high_dollars": "0.0590", "low_dollars": "0.0590", "open_dollars": "0.0590"}}, {"end_period_ts": 1780977600, "open_interest_fp": "2471051.49", "price": {"close_dollars": "0.0600", "high_dollars": "0.0600", "low_dollars": "0.0590", "mean_dollars": "0.0599", "open_dollars": "0.0600", "previous_dollars": "0.0600"}, "volume_fp": "133381.51", "yes_ask": {"close_dollars": "0.0600", "high_dollars": "0.0600", "low_dollars": "0.0600", "open_dollars": "0.0600"}, "yes_bid": {"close_dollars": "0.0590", "high_dollars": "0.0590", "low_dollars": "0.0590", "open_dollars": "0.0590"}}, {"end_period_ts": 1781064000, "open_interest_fp": "2569957.41", "price": {"close_dollars": "0.0590", "high_dollars": "0.0600", "low_dollars": "0.0580", "mean_dollars": "0.0595", "open_dollars": "0.0600", "previous_dollars": "0.0600"}, "volume_fp": "133530.36", "yes_ask": {"close_dollars": "0.0590", "high_dollars": "0.0600", "low_dollars": "0.0590", "open_dollars": "0.0600"}, "yes_bid": {"close_dollars": "0.0580", "high_dollars": "0.0590", "low_dollars": "0.0580", "open_dollars": "0.0590"}}, {"end_period_ts": 1781150400, "open_interest_fp": "2936050.49", "price": {"close_dollars": "0.0560", "high_dollars": "0.0590", "low_dollars": "0.0510", "mean_dollars": "0.0560", "open_dollars": "0.0590", "previous_dollars": "0.0590"}, "volume_fp": "469485.17", "yes_ask": {"close_dollars": "0.0560", "high_dollars": "0.0590", "low_dollars": "0.0550", "open_dollars": "0.0590"}, "yes_bid": {"close_dollars": "0.0550", "high_dollars": "0.0580", "low_dollars": "0.0500", "open_dollars": "0.0580"}}, {"end_period_ts": 1781236800, "open_interest_fp": "3512188.20", "price": {"close_dollars": "0.0560", "high_dollars": "0.0560", "low_dollars": "0.0550", "mean_dollars": "0.0560", "open_dollars": "0.0560", "previous_dollars": "0.0560"}, "volume_fp": "615566.58", "yes_ask": {"close_dollars": "0.0560", "high_dollars": "0.0560", "low_dollars": "0.0560", "open_dollars": "0.0560"}, "yes_bid": {"close_dollars": "0.0550", "high_dollars": "0.0550", "low_dollars": "0.0550", "open_dollars": "0.0550"}}, {"end_period_ts": 1781323200, "open_interest_fp": "4763586.72", "price": {"close_dollars": "0.0510", "high_dollars": "0.0560", "low_dollars": "0.0500", "mean_dollars": "0.0551", "open_dollars": "0.0560", "previous_dollars": "0.0560"}, "volume_fp": "1310322.83", "yes_ask": {"close_dollars": "0.0510", "high_dollars": "0.0560", "low_dollars": "0.0510", "open_dollars": "0.0560"}, "yes_bid": {"close_dollars": "0.0500", "high_dollars": "0.0550", "low_dollars": "0.0500", "open_dollars": "0.0550"}}, {"end_period_ts": 1781409600, "open_interest_fp": "5191224.00", "price": {"close_dollars": "0.0510", "high_dollars": "0.0510", "low_dollars": "0.0500", "mean_dollars": "0.0510", "open_dollars": "0.0510", "previous_dollars": "0.0510"}, "volume_fp": "459000.18", "yes_ask": {"close_dollars": "0.0510", "high_dollars": "0.0520", "low_dollars": "0.0510", "open_dollars": "0.0510"}, "yes_bid": {"close_dollars": "0.0500", "high_dollars": "0.0510", "low_dollars": "0.0500", "open_dollars": "0.0500"}}, {"end_period_ts": 1781496000, "open_interest_fp": "6200882.69", "price": {"close_dollars": "0.0600", "high_dollars": "0.0610", "low_dollars": "0.0500", "mean_dollars": "0.0544", "open_dollars": "0.0510", "previous_dollars": "0.0510"}, "volume_fp": "1193505.66", "yes_ask": {"close_dollars": "0.0600", "high_dollars": "0.0610", "low_dollars": "0.0510", "open_dollars": "0.0510"}, "yes_bid": {"close_dollars": "0.0580", "high_dollars": "0.0600", "low_dollars": "0.0500", "open_dollars": "0.0500"}}, {"end_period_ts": 1781582400, "open_interest_fp": "6831767.20", "price": {"close_dollars": "0.0620", "high_dollars": "0.0630", "low_dollars": "0.0560", "mean_dollars": "0.0607", "open_dollars": "0.0590", "previous_dollars": "0.0600"}, "volume_fp": "855857.08", "yes_ask": {"close_dollars": "0.0620", "high_dollars": "0.0630", "low_dollars": "0.0570", "open_dollars": "0.0600"}, "yes_bid": {"close_dollars": "0.0610", "high_dollars": "0.0610", "low_dollars": "0.0560", "open_dollars": "0.0580"}}, {"end_period_ts": 1781668800, "open_interest_fp": "7392716.42", "price": {"close_dollars": "0.0610", "high_dollars": "0.0630", "low_dollars": "0.0600", "mean_dollars": "0.0618", "open_dollars": "0.0620", "previous_dollars": "0.0620"}, "volume_fp": "653768.44", "yes_ask": {"close_dollars": "0.0610", "high_dollars": "0.0640", "low_dollars": "0.0610", "open_dollars": "0.0620"}, "yes_bid": {"close_dollars": "0.0600", "high_dollars": "0.0620", "low_dollars": "0.0600", "open_dollars": "0.0610"}}, {"end_period_ts": 1781755200, "open_interest_fp": "7797279.57", "price": {"close_dollars": "0.0580", "high_dollars": "0.0610", "low_dollars": "0.0560", "mean_dollars": "0.0601", "open_dollars": "0.0610", "previous_dollars": "0.0610"}, "volume_fp": "594865.56", "yes_ask": {"close_dollars": "0.0580", "high_dollars": "0.0610", "low_dollars": "0.0570", "open_dollars": "0.0610"}, "yes_bid": {"close_dollars": "0.0570", "high_dollars": "0.0600", "low_dollars": "0.0560", "open_dollars": "0.0600"}}, {"end_period_ts": 1781841600, "open_interest_fp": "8469808.37", "price": {"close_dollars": "0.0610", "high_dollars": "0.0610", "low_dollars": "0.0560", "mean_dollars": "0.0593", "open_dollars": "0.0580", "previous_dollars": "0.0580"}, "volume_fp": "735841.50", "yes_ask": {"close_dollars": "0.0610", "high_dollars": "0.0610", "low_dollars": "0.0580", "open_dollars": "0.0580"}, "yes_bid": {"close_dollars": "0.0600", "high_dollars": "0.0600", "low_dollars": "0.0560", "open_dollars": "0.0570"}}, {"end_period_ts": 1781928000, "open_interest_fp": "8795820.16", "price": {"close_dollars": "0.0600", "high_dollars": "0.0610", "low_dollars": "0.0590", "mean_dollars": "0.0604", "open_dollars": "0.0610", "previous_dollars": "0.0610"}, "volume_fp": "448078.95", "yes_ask": {"close_dollars": "0.0600", "high_dollars": "0.0610", "low_dollars": "0.0600", "open_dollars": "0.0610"}, "yes_bid": {"close_dollars": "0.0590", "high_dollars": "0.0600", "low_dollars": "0.0590", "open_dollars": "0.0600"}}, {"end_period_ts": 1782014400, "open_interest_fp": "9632255.54", "price": {"close_dollars": "0.0600", "high_dollars": "0.0700", "low_dollars": "0.0450", "mean_dollars": "0.0592", "open_dollars": "0.0600", "previous_dollars": "0.0600"}, "volume_fp": "1274140.30", "yes_ask": {"close_dollars": "0.0600", "high_dollars": "0.0700", "low_dollars": "0.0470", "open_dollars": "0.0600"}, "yes_bid": {"close_dollars": "0.0590", "high_dollars": "0.0640", "low_dollars": "0.0450", "open_dollars": "0.0590"}}, {"end_period_ts": 1782100800, "open_interest_fp": "9955451.55", "price": {"close_dollars": "0.0570", "high_dollars": "0.0600", "low_dollars": "0.0510", "mean_dollars": "0.0581", "open_dollars": "0.0580", "previous_dollars": "0.0600"}, "volume_fp": "579072.41", "yes_ask": {"close_dollars": "0.0570", "high_dollars": "0.0600", "low_dollars": "0.0530", "open_dollars": "0.0600"}, "yes_bid": {"close_dollars": "0.0560", "high_dollars": "0.0590", "low_dollars": "0.0500", "open_dollars": "0.0590"}}, {"end_period_ts": 1782187200, "open_interest_fp": "10385379.22", "price": {"close_dollars": "0.0550", "high_dollars": "0.0570", "low_dollars": "0.0500", "mean_dollars": "0.0565", "open_dollars": "0.0570", "previous_dollars": "0.0570"}, "volume_fp": "534533.72", "yes_ask": {"close_dollars": "0.0550", "high_dollars": "0.0570", "low_dollars": "0.0520", "open_dollars": "0.0570"}, "yes_bid": {"close_dollars": "0.0540", "high_dollars": "0.0560", "low_dollars": "0.0500", "open_dollars": "0.0560"}}, {"end_period_ts": 1782273600, "open_interest_fp": "10795120.28", "price": {"close_dollars": "0.0510", "high_dollars": "0.0580", "low_dollars": "0.0450", "mean_dollars": "0.0528", "open_dollars": "0.0550", "previous_dollars": "0.0550"}, "volume_fp": "557296.73", "yes_ask": {"close_dollars": "0.0540", "high_dollars": "0.0580", "low_dollars": "0.0490", "open_dollars": "0.0550"}, "yes_bid": {"close_dollars": "0.0520", "high_dollars": "0.0560", "low_dollars": "0.0450", "open_dollars": "0.0540"}}, {"end_period_ts": 1782360000, "open_interest_fp": "11165604.81", "price": {"close_dollars": "0.0530", "high_dollars": "0.0580", "low_dollars": "0.0490", "mean_dollars": "0.0534", "open_dollars": "0.0540", "previous_dollars": "0.0510"}, "volume_fp": "455742.70", "yes_ask": {"close_dollars": "0.0530", "high_dollars": "0.0580", "low_dollars": "0.0520", "open_dollars": "0.0540"}, "yes_bid": {"close_dollars": "0.0520", "high_dollars": "0.0550", "low_dollars": "0.0490", "open_dollars": "0.0520"}}, {"end_period_ts": 1782446400, "open_interest_fp": "11610660.41", "price": {"close_dollars": "0.0450", "high_dollars": "0.0530", "low_dollars": "0.0200", "mean_dollars": "0.0464", "open_dollars": "0.0530", "previous_dollars": "0.0530"}, "volume_fp": "911088.92", "yes_ask": {"close_dollars": "0.0450", "high_dollars": "0.0530", "low_dollars": "0.0370", "open_dollars": "0.0530"}, "yes_bid": {"close_dollars": "0.0440", "high_dollars": "0.0520", "low_dollars": "0.0200", "open_dollars": "0.0520"}}, {"end_period_ts": 1782532800, "open_interest_fp": "11754249.18", "price": {"close_dollars": "0.0450", "high_dollars": "0.0490", "low_dollars": "0.0400", "mean_dollars": "0.0455", "open_dollars": "0.0440", "previous_dollars": "0.0450"}, "volume_fp": "367669.28", "yes_ask": {"close_dollars": "0.0460", "high_dollars": "0.0490", "low_dollars": "0.0440", "open_dollars": "0.0450"}, "yes_bid": {"close_dollars": "0.0450", "high_dollars": "0.0470", "low_dollars": "0.0400", "open_dollars": "0.0440"}}, {"end_period_ts": 1782619200, "open_interest_fp": "12818045.04", "price": {"close_dollars": "0.0410", "high_dollars": "0.0460", "low_dollars": "0.0330", "mean_dollars": "0.0419", "open_dollars": "0.0460", "previous_dollars": "0.0450"}, "volume_fp": "1973765.53", "yes_ask": {"close_dollars": "0.0420", "high_dollars": "0.0460", "low_dollars": "0.0390", "open_dollars": "0.0460"}, "yes_bid": {"close_dollars": "0.0410", "high_dollars": "0.0450", "low_dollars": "0.0330", "open_dollars": "0.0450"}}, {"end_period_ts": 1782705600, "open_interest_fp": "13558720.04", "price": {"close_dollars": "0.0360", "high_dollars": "0.0420", "low_dollars": "0.0360", "mean_dollars": "0.0369", "open_dollars": "0.0420", "previous_dollars": "0.0410"}, "volume_fp": "1051147.79", "yes_ask": {"close_dollars": "0.0370", "high_dollars": "0.0420", "low_dollars": "0.0370", "open_dollars": "0.0420"}, "yes_bid": {"close_dollars": "0.0360", "high_dollars": "0.0410", "low_dollars": "0.0360", "open_dollars": "0.0410"}}, {"end_period_ts": 1782792000, "open_interest_fp": "14657720.61", "price": {"close_dollars": "0.0010", "high_dollars": "0.0530", "low_dollars": "0.0010", "mean_dollars": "0.0291", "open_dollars": "0.0370", "previous_dollars": "0.0360"}, "volume_fp": "1728738.84", "yes_ask": {"close_dollars": "1.0000", "high_dollars": "1.0000", "low_dollars": "0.0010", "open_dollars": "0.0370"}, "yes_bid": {"close_dollars": "0.0000", "high_dollars": "0.0440", "low_dollars": "0.0000", "open_dollars": "0.0360"}}], "ticker": "KXMENWORLDCUP-26-DE"}